<Properties GitUserInfo="UsingMD" StartupConfiguration="{244CC991-420C-41C4-B98E-0AEA8AEB865F}|Default">
  <MonoDevelop.Ide.Workspace ActiveConfiguration="Debug" />
  <MultiItemStartupConfigurations />
  <MonoDevelop.Ide.DebuggingService.PinnedWatches />
  <MonoDevelop.Ide.DebuggingService.Breakpoints>
    <BreakpointStore />
  </MonoDevelop.Ide.DebuggingService.Breakpoints>
  <MonoDevelop.Ide.ItemProperties.TravelEase__WebService PreferredExecutionTarget="/System/Volumes/Preboot/Cryptexes/App/System/Applications/Safari.app" />
  <MonoDevelop.Ide.Workbench ActiveDocument="Controllers/TravellerManagement/ProfileActivationController.cs">
    <Files>
      <File FileName="Controllers/UserManagement/AuthenticationController.cs" Line="25" Column="1" IsPinned="True" />
      <File FileName="Dtos/UserManagement/LoginResponse.cs" Line="15" Column="1" IsPinned="True" />
      <File FileName="Program.cs" Line="17" Column="1" IsPinned="True" />
      <File FileName="Controllers/TravellerManagement/TravellerProfileController.cs" Line="9" Column="16" />
      <File FileName="Controllers/TravellerManagement/ProfileActivationController.cs" Line="14" Column="1" />
    </Files>
    <Pads>
      <Pad Id="ProjectPad">
        <State name="__root__">
          <Node name="TravelEase_WebService">
            <Node name="TravelEase_WebService">
              <Node name="Controllers">
                <Node name="TravellerManagement">
                  <Node name="ProfileActivationController.cs" selected="True" />
                </Node>
                <Node name="UserManagement" expanded="True" />
              </Node>
              <Node name="Dtos" expanded="True">
                <Node name="UserManagement" expanded="True" />
              </Node>
            </Node>
          </Node>
        </State>
      </Pad>
    </Pads>
  </MonoDevelop.Ide.Workbench>
</Properties>